{"boundaries": {"type": "FeatureCollection", "features": []}, "buildings": {"type": "FeatureCollection", "features": [{"geometry": {"type": "Polygon", "coordinates": [[[0.054914, 51.532824], [0.05574, 51.532937], [0.055799, 51.532746], [0.055641, 51.532725], [0.05566, 51.532677], [0.055834, 51.532697], [0.055909, 51.532504], [0.055555, 51.532447], [0.055563, 51.532387], [0.055204, 51.532345], [0.055153, 51.53234], [0.055032, 51.53271], [0.054957, 51.532707], [0.054914, 51.532824]]]}, "type": "Feature", "properties": {"source": "openstreetmap.org", "kind": "building", "landuse_kind": "commercial", "id": 118968996, "area": 7478}}, {"geometry": {"type": "Polygon", "coordinates": [[[0.055918, 51.533057], [0.056459, 51.533121], [0.05656, 51.532787], [0.056019, 51.532723], [0.055918, 51.533057]]]}, "type": "Feature", "properties": {"kind": "building", "name": "Old Tech College", "area": 3730, "landuse_kind": "commercial", "source": "openstreetmap.org", "old_name": "East Ham Technical College", "id": 30252292}}, {"geometry": {"type": "Point", "coordinates": [0.056239, 51.532922]}, "type": "Feature", "properties": {"label_placement": "yes", "kind": "building", "name": "Old Tech College", "area": 3730, "landuse_kind": "commercial", "source": "openstreetmap.org", "old_name": "East Ham Technical College", "id": 30252292}}, {"geometry": {"type": "Polygon", "coordinates": [[[0.05791, 51.53336], [0.058573, 51.533443], [0.058581, 51.533401], [0.058541, 51.5334], [0.058549, 51.533373], [0.058522, 51.533371], [0.058554, 51.533258], [0.058594, 51.533263], [0.058616, 51.533208], [0.058554, 51.533199], [0.058559, 51.533178], [0.058428, 51.533161], [0.058232, 51.533131], [0.058133, 51.533118], [0.058074, 51.533113], [0.058066, 51.533134], [0.058028, 51.533126], [0.058015, 51.533174], [0.058036, 51.533178], [0.057993, 51.533291], [0.057958, 51.533289], [0.057953, 51.533313], [0.057921, 51.533309], [0.05791, 51.53336]]]}, "type": "Feature", "properties": {"source": "openstreetmap.org", "kind": "building", "landuse_kind": "commercial", "id": 118972072, "area": 3006}}]}, "landuse_labels": {"type": "FeatureCollection", "features": []}, "places": {"type": "FeatureCollection", "features": [{"geometry": {"type": "Point", "coordinates": [0.05532, 51.532963]}, "type": "Feature", "properties": {"source": "openstreetmap", "kind": "town", "scalerank": 8, "name": "East Ham", "id": 3942034573}}]}, "transit": {"type": "FeatureCollection", "features": []}, "pois": {"type": "FeatureCollection", "features": [{"geometry": {"type": "Point", "coordinates": [0.055204, 51.535291]}, "type": "Feature", "properties": {"kind": "mini_roundabout", "id": 117944135}}, {"geometry": {"type": "Point", "coordinates": [0.058997, 51.533745]}, "type": "Feature", "properties": {"kind": "post_office", "id": 268523611}}, {"geometry": {"type": "Point", "coordinates": [0.055839, 51.53317]}, "type": "Feature", "properties": {"kind": "gate", "id": 333284377}}]}, "water": {"type": "FeatureCollection", "features": []}, "roads": {"type": "FeatureCollection", "features": [{"geometry": {"type": "LineString", "coordinates": [[0.058779, 51.533957], [0.058203, 51.535584]]}, "type": "Feature", "properties": {"kind": "minor_road", "name": "Altmore Ave.", "sort_key": 17, "landuse_kind": "residential", "source": "openstreetmap", "id": 12869709, "highway": "residential"}}, {"geometry": {"type": "LineString", "coordinates": [[0.055811, 51.533252], [0.055839, 51.53317], [0.055845, 51.533148]]}, "type": "Feature", "properties": {"sort_key": 16, "source": "openstreetmap", "kind": "minor_road", "id": 30252433, "highway": "service"}}, {"geometry": {"type": "LineString", "coordinates": [[0.059044, 51.533183], [0.059291, 51.533242], [0.059365, 51.533043], [0.059547, 51.533068], [0.059713, 51.532704], [0.060094, 51.532745], [0.060118, 51.532669]]}, "type": "Feature", "properties": {"kind": "path", "name": "Drakes Walk", "sort_key": 15, "landuse_kind": "residential", "source": "openstreetmap", "id": 24705413, "highway": "footway"}}, {"geometry": {"type": "LineString", "coordinates": [[0.057751, 51.533361], [0.057707, 51.533488]]}, "type": "Feature", "properties": {"kind": "minor_road", "name": "Wellington Rd.", "sort_key": 17, "source": "openstreetmap", "id": 24705303, "highway": "residential"}}, {"geometry": {"type": "LineString", "coordinates": [[0.057993, 51.532669], [0.057751, 51.533361]]}, "type": "Feature", "properties": {"kind": "minor_road", "name": "Wellington Rd.", "sort_key": 17, "landuse_kind": "commercial", "source": "openstreetmap", "id": 24705303, "highway": "residential"}}, {"geometry": {"type": "MultiLineString", "coordinates": [[[0.059158, 51.535711], [0.059118, 51.535825], [0.059014, 51.536086]], [[0.059855, 51.533721], [0.05985, 51.533737]]]}, "type": "Feature", "properties": {"kind": "minor_road", "name": "Hall Rd.", "sort_key": 17, "source": "openstreetmap", "id": 12869535, "highway": "residential"}}, {"geometry": {"type": "LineString", "coordinates": [[0.058888, 51.53365], [0.05879, 51.533926]]}, "type": "Feature", "properties": {"kind": "minor_road", "name": "Altmore Ave.", "sort_key": 17, "landuse_kind": "retail", "source": "openstreetmap", "id": 12869709, "highway": "residential"}}, {"geometry": {"type": "LineString", "coordinates": [[0.054932, 51.534273], [0.055669, 51.534366]]}, "type": "Feature", "properties": {"kind": "minor_road", "name": "Thorpe Rd.", "sort_key": 17, "landuse_kind": "residential", "source": "openstreetmap", "oneway": "yes", "id": 12869557, "highway": "residential"}}, {"geometry": {"type": "LineString", "coordinates": [[0.056873, 51.53372], [0.056322, 51.535333]]}, "type": "Feature", "properties": {"kind": "minor_road", "name": "Streatfeild Ave.", "sort_key": 17, "landuse_kind": "residential", "source": "openstreetmap", "id": 12869620, "highway": "residential"}}, {"geometry": {"type": "LineString", "coordinates": [[0.056971, 51.533433], [0.05688, 51.533698]]}, "type": "Feature", "properties": {"kind": "minor_road", "name": "Streatfeild Ave.", "sort_key": 17, "landuse_kind": "retail", "source": "openstreetmap", "id": 12869620, "highway": "residential"}}, {"geometry": {"type": "LineString", "coordinates": [[0.058995, 51.53294], [0.058927, 51.533155]]}, "type": "Feature", "properties": {"kind": "path", "name": "Melbourne Rd.", "sort_key": 15, "source": "openstreetmap", "id": 24705305, "highway": "footway"}}, {"geometry": {"type": "LineString", "coordinates": [[0.054932, 51.535894], [0.056375, 51.536086]]}, "type": "Feature", "properties": {"kind": "minor_road", "name": "Skeffington Rd.", "sort_key": 17, "landuse_kind": "residential", "source": "openstreetmap", "id": 99951744, "highway": "residential"}}, {"geometry": {"type": "LineString", "coordinates": [[0.058927, 51.533155], [0.059044, 51.533183]]}, "type": "Feature", "properties": {"kind": "path", "name": "Drakes Walk", "sort_key": 15, "source": "openstreetmap", "id": 24705413, "highway": "footway"}}, {"geometry": {"type": "LineString", "coordinates": [[0.057973, 51.533549], [0.057871, 51.533819]]}, "type": "Feature", "properties": {"kind": "minor_road", "name": "Latimer Ave.", "sort_key": 17, "landuse_kind": "retail", "source": "openstreetmap", "id": 12869624, "highway": "residential"}}, {"geometry": {"type": "MultiLineString", "coordinates": [[[0.055259, 51.535186], [0.055204, 51.535291], [0.055194, 51.535308]], [[0.056035, 51.533283], [0.056021, 51.533324]]]}, "type": "Feature", "properties": {"kind": "minor_road", "name": "Keppel Rd.", "sort_key": 17, "source": "openstreetmap", "id": 12864221, "highway": "residential"}}, {"geometry": {"type": "LineString", "coordinates": [[0.060425, 51.534665], [0.060039, 51.535828]]}, "type": "Feature", "properties": {"kind": "minor_road", "name": "Norfolk Rd.", "sort_key": 17, "landuse_kind": "residential", "source": "openstreetmap", "id": 12893273, "highway": "residential"}}, {"geometry": {"type": "MultiLineString", "coordinates": [[[0.057249, 51.535456], [0.05721, 51.535561]], [[0.057871, 51.533819], [0.057851, 51.53387]], [[0.057982, 51.533526], [0.057973, 51.533549]]]}, "type": "Feature", "properties": {"kind": "minor_road", "name": "Latimer Ave.", "sort_key": 17, "source": "openstreetmap", "id": 12869624, "highway": "residential"}}, {"geometry": {"type": "LineString", "coordinates": [[0.059088, 51.532669], [0.058995, 51.53294]]}, "type": "Feature", "properties": {"kind": "minor_road", "name": "Melbourne Rd.", "sort_key": 17, "source": "openstreetmap", "id": 12863540, "highway": "residential"}}, {"geometry": {"type": "MultiLineString", "coordinates": [[[0.055204, 51.535291], [0.056285, 51.535441], [0.05721, 51.535561], [0.058165, 51.535692], [0.058249, 51.535703]], [[0.059069, 51.535818], [0.059118, 51.535825], [0.06, 51.535945], [0.060425, 51.536]]]}, "type": "Feature", "properties": {"kind": "minor_road", "name": "Kempton Rd.", "sort_key": 17, "source": "openstreetmap", "id": 30251955, "highway": "residential"}}, {"geometry": {"type": "LineString", "coordinates": [[0.059724, 51.533708], [0.059767, 51.533579]]}, "type": "Feature", "properties": {"kind": "minor_road", "name": "Canberra Rd.", "sort_key": 17, "source": "openstreetmap", "id": 108514027, "highway": "residential"}}, {"geometry": {"type": "LineString", "coordinates": [[0.057851, 51.53387], [0.057249, 51.535456]]}, "type": "Feature", "properties": {"kind": "minor_road", "name": "Latimer Ave.", "sort_key": 17, "landuse_kind": "residential", "source": "openstreetmap", "id": 12869624, "highway": "residential"}}, {"geometry": {"type": "LineString", "coordinates": [[0.058249, 51.535703], [0.059069, 51.535818]]}, "type": "Feature", "properties": {"kind": "minor_road", "name": "Kempton Rd.", "sort_key": 17, "landuse_kind": "school", "source": "openstreetmap", "id": 30251955, "highway": "residential"}}, {"geometry": {"type": "LineString", "coordinates": [[0.055845, 51.533148], [0.05598, 51.532669]]}, "type": "Feature", "properties": {"kind": "minor_road", "sort_key": 16, "landuse_kind": "commercial", "source": "openstreetmap", "id": 30252433, "highway": "service"}}, {"geometry": {"type": "LineString", "coordinates": [[0.056021, 51.533324], [0.055934, 51.533584]]}, "type": "Feature", "properties": {"kind": "minor_road", "name": "Keppel Rd.", "sort_key": 17, "landuse_kind": "retail", "source": "openstreetmap", "id": 12864221, "highway": "residential"}}, {"geometry": {"type": "MultiLineString", "coordinates": [[[0.056322, 51.535333], [0.056285, 51.535441]], [[0.05688, 51.533698], [0.056873, 51.53372]], [[0.056982, 51.533399], [0.056971, 51.533433]]]}, "type": "Feature", "properties": {"kind": "minor_road", "name": "Streatfeild Ave.", "sort_key": 17, "source": "openstreetmap", "id": 12869620, "highway": "residential"}}, {"geometry": {"type": "LineString", "coordinates": [[0.05985, 51.533737], [0.05976, 51.533994]]}, "type": "Feature", "properties": {"kind": "minor_road", "name": "Hall Rd.", "sort_key": 17, "landuse_kind": "retail", "source": "openstreetmap", "id": 12869535, "highway": "residential"}}, {"geometry": {"type": "MultiLineString", "coordinates": [[[0.058203, 51.535584], [0.058165, 51.535692], [0.05802, 51.536086]], [[0.05879, 51.533926], [0.058779, 51.533957]], [[0.058895, 51.533629], [0.058888, 51.53365]]]}, "type": "Feature", "properties": {"kind": "minor_road", "name": "Altmore Ave.", "sort_key": 17, "source": "openstreetmap", "id": 12869709, "highway": "residential"}}, {"geometry": {"type": "LineString", "coordinates": [[0.060425, 51.533781], [0.059855, 51.533721], [0.059724, 51.533708], [0.058895, 51.533629], [0.058734, 51.533616], [0.057982, 51.533526], [0.057707, 51.533488], [0.056982, 51.533399], [0.056035, 51.533283], [0.055811, 51.533252], [0.054932, 51.533142]]}, "type": "Feature", "properties": {"kind": "major_road", "name": "Barking Rd.", "sort_key": 21, "source": "openstreetmap", "ref": "A124", "id": 227704882, "highway": "primary", "network": "lcn"}}, {"geometry": {"type": "LineString", "coordinates": [[0.060039, 51.535828], [0.06, 51.535945]]}, "type": "Feature", "properties": {"kind": "minor_road", "name": "Norfolk Rd.", "sort_key": 17, "source": "openstreetmap", "id": 12893273, "highway": "residential"}}, {"geometry": {"type": "LineString", "coordinates": [[0.055204, 51.535291], [0.054932, 51.535236]]}, "type": "Feature", "properties": {"kind": "minor_road", "name": "Kempton Rd.", "sort_key": 17, "source": "openstreetmap", "oneway": "yes", "id": 12869079, "highway": "residential"}}, {"geometry": {"type": "MultiLineString", "coordinates": [[[0.059767, 51.533579], [0.059826, 51.533404]], [[0.059826, 51.533404], [0.059891, 51.533209]], [[0.059826, 51.533404], [0.060095, 51.533434]]]}, "type": "Feature", "properties": {"kind": "minor_road", "name": "Canberra Rd.", "sort_key": 17, "landuse_kind": "residential", "source": "openstreetmap", "id": 108514026, "highway": "residential"}}, {"geometry": {"type": "MultiLineString", "coordinates": [[[0.055194, 51.535308], [0.054932, 51.535771]], [[0.055934, 51.533584], [0.055849, 51.533838], [0.055669, 51.534366], [0.055673, 51.534391], [0.055382, 51.534951], [0.055259, 51.535186]]]}, "type": "Feature", "properties": {"kind": "minor_road", "name": "Keppel Rd.", "sort_key": 17, "landuse_kind": "residential", "source": "openstreetmap", "id": 12864221, "highway": "residential"}}, {"geometry": {"type": "LineString", "coordinates": [[0.055849, 51.533838], [0.054932, 51.533719]]}, "type": "Feature", "properties": {"kind": "minor_road", "name": "Lloyd Rd.", "sort_key": 17, "landuse_kind": "residential", "source": "openstreetmap", "oneway": "yes", "id": 12869587, "highway": "residential"}}, {"geometry": {"type": "LineString", "coordinates": [[0.05976, 51.533994], [0.059158, 51.535711]]}, "type": "Feature", "properties": {"kind": "minor_road", "name": "Hall Rd.", "sort_key": 17, "landuse_kind": "residential", "source": "openstreetmap", "id": 12869535, "highway": "residential"}}, {"geometry": {"type": "LineString", "coordinates": [[0.058927, 51.533155], [0.058734, 51.533616]]}, "type": "Feature", "properties": {"kind": "minor_road", "name": "Didsbury Close", "sort_key": 17, "source": "openstreetmap", "id": 24705168, "highway": "residential"}}]}, "earth": {"type": "FeatureCollection", "features": [{"geometry": {"type": "Polygon", "coordinates": [[[0.060425, 51.532669], [0.054932, 51.532669], [0.054932, 51.536086], [0.060425, 51.536086], [0.060425, 51.532669]]]}, "type": "Feature", "properties": {"land": "base", "id": 44864}}]}, "landuse": {"type": "FeatureCollection", "features": [{"geometry": {"type": "Polygon", "coordinates": [[[0.060425, 51.53603], [0.059215, 51.535877], [0.059125, 51.536086], [0.060425, 51.536086], [0.060425, 51.53603]]]}, "type": "Feature", "properties": {"kind": "residential", "area": 395275, "sort_key": 1, "source": "openstreetmap.org", "min_zoom": 9.0, "id": 48700043}}, {"geometry": {"type": "MultiPolygon", "coordinates": [[[[0.054932, 51.534726], [0.055043, 51.534594], [0.054932, 51.534581], [0.054932, 51.534726]]], [[[0.054932, 51.533462], [0.058702, 51.53392], [0.060425, 51.53404], [0.060425, 51.533789], [0.058702, 51.533633], [0.054932, 51.533198], [0.054932, 51.533462]]]]}, "type": "Feature", "properties": {"kind": "retail", "area": 359074, "sort_key": 4, "source": "openstreetmap.org", "min_zoom": 9.0, "id": 48701995}}, {"geometry": {"type": "Polygon", "coordinates": [[[0.054932, 51.535127], [0.055352, 51.535203], [0.060425, 51.53588], [0.060425, 51.534073], [0.05929, 51.533929], [0.059054, 51.533982], [0.057616, 51.533849], [0.056264, 51.533615], [0.054932, 51.533466], [0.054932, 51.534575], [0.054987, 51.534583], [0.054932, 51.534767], [0.054932, 51.535127]]]}, "type": "Feature", "properties": {"kind": "residential", "area": 354839, "sort_key": 1, "source": "openstreetmap.org", "min_zoom": 9.0, "id": 48700048}}, {"geometry": {"type": "Polygon", "coordinates": [[[0.057955, 51.536086], [0.058099, 51.53569], [0.055374, 51.535343], [0.054932, 51.535256], [0.054932, 51.536086], [0.057955, 51.536086]]]}, "type": "Feature", "properties": {"kind": "residential", "area": 325476, "sort_key": 1, "source": "openstreetmap.org", "min_zoom": 9.0, "id": 48700044}}, {"geometry": {"type": "Polygon", "coordinates": [[[0.059216, 51.532669], [0.058936, 51.533508], [0.059955, 51.533595], [0.060425, 51.533637], [0.060425, 51.532669], [0.059216, 51.532669]]]}, "type": "Feature", "properties": {"kind": "residential", "area": 153276, "sort_key": 1, "source": "openstreetmap.org", "min_zoom": 9.0, "id": 48700036}}, {"geometry": {"type": "Polygon", "coordinates": [[[0.054932, 51.533046], [0.058737, 51.533472], [0.059015, 51.532669], [0.054932, 51.532669], [0.054932, 51.533046]]]}, "type": "Feature", "properties": {"kind": "commercial", "area": 123353, "sort_key": 4, "source": "openstreetmap.org", "min_zoom": 9.0, "id": 48702187}}, {"geometry": {"type": "Polygon", "coordinates": [[[0.058962, 51.536086], [0.059079, 51.535793], [0.058255, 51.535686], [0.058107, 51.536086], [0.058962, 51.536086]]]}, "type": "Feature", "properties": {"kind": "school", "area": 19506, "sort_key": 4, "source": "openstreetmap.org", "min_zoom": 10.1302, "id": 30694838}}]}}